fusebox/__init__.py
fusebox/container.py
fusebox/decorators.py
fusebox/test_container.py
fusebox/test_decorators.py
fusebox-0.0.1.dist-info/LICENSE
fusebox-0.0.1.dist-info/METADATA
fusebox-0.0.1.dist-info/WHEEL
fusebox-0.0.1.dist-info/RECORD
