Metadata-Version: 2.3
Name: fusebox
Version: 0.0.1
Summary: A lightweight and Pythonic dependency injection container
License: MIT
Author: Filip Tanurovski
Author-email: filip@tanurov.ski
Requires-Python: >=3.9,<4.0
Classifier: License :: OSI Approved :: MIT License
Classifier: Programming Language :: Python :: 3
Classifier: Programming Language :: Python :: 3.9
Classifier: Programming Language :: Python :: 3.10
Classifier: Programming Language :: Python :: 3.11
Classifier: Programming Language :: Python :: 3.12
Classifier: Programming Language :: Python :: 3.13
